API7/__init__.py
API7/api_error.py
API7/http_interactor.py
API7/schemas.py
API7/sdk.py
API7/util.py
API7/collections/collections_manager.py
API7/collections/schemas.py
API7/compare/compare_manager.py
API7/compare/schemas.py
API7/liveness/liveness_manager.py
API7/liveness/schemas.py
API7/persons/persons_manager.py
API7/persons/schemas.py
API7/search/schemas.py
API7/search/search_manager.py
API7-0.0.3.dist-info/LICENSE
API7-0.0.3.dist-info/METADATA
API7-0.0.3.dist-info/WHEEL
API7-0.0.3.dist-info/top_level.txt
API7-0.0.3.dist-info/RECORD
