Metadata-Version: 2.1
Name: API7
Version: 0.0.3
Summary: Python SDK for interacting with API7 Facial Recognition Server
Author-email: Seventh Sense Artificial Intelligence Private Limited <support@seventhsense.ai>
License: The MIT License (MIT)
Project-URL: Homepage, https://docs.api7cloud.com/python
Keywords: API7,Facial Verification,Facial Recognition
Classifier: License :: OSI Approved :: MIT License
Classifier: Programming Language :: Python
Classifier: Programming Language :: Python :: 3
Requires-Python: >=3.8
License-File: LICENSE
Requires-Dist: numpy
Requires-Dist: opencv-python
Requires-Dist: pillow
Requires-Dist: python-dateutil
Requires-Dist: requests
Provides-Extra: dev
Requires-Dist: jupyter ; extra == 'dev'
Requires-Dist: mkdocs ; extra == 'dev'
